.hgignore
.hgtags
publish.sh
screen.png
setup.py
altf2/__init__.py
altf2/app.py
altf2.egg-info/PKG-INFO
altf2.egg-info/SOURCES.txt
altf2.egg-info/dependency_links.txt
altf2.egg-info/entry_points.txt
altf2.egg-info/top_level.txt
altf2/ui/__init__.py
altf2/ui/main.py
altf2/ui/main.ui
altf2/ui/mycombobox.py