Metadata-Version: 1.1
Name: altf2
Version: 1.1.0
Summary: Simple program runner (Alt-F2 handler). Requires PyQt5
Home-page: https://bitbucket.org/angry_elf/altf2
Author: Alexey Elfman
Author-email: elf2001@gmail.com
License: GPL
Platform: UNKNOWN
Classifier: Development Status :: 5 - Production/Stable
Classifier: Environment :: X11 Applications
Classifier: Environment :: X11 Applications :: Qt
Classifier: Intended Audience :: End Users/Desktop
Classifier: License :: OSI Approved :: GNU General Public License (GPL)
Classifier: Natural Language :: English
Classifier: Programming Language :: Python
Classifier: Operating System :: POSIX
Classifier: Topic :: Desktop Environment
Classifier: Topic :: Utilities
